pyCRT/__about__.py
pyCRT/__init__.py
pyCRT/arrayOperations.py
pyCRT/arrayPlotting.py
pyCRT/configFiles.py
pyCRT/curveFitting.py
pyCRT/frameOperations.py
pyCRT/simpleUI.py
pyCRT/videoReading.py
pyCRT/cameraConfigs/DFK23UP031.toml
pyCRT/cameraConfigs/genericCamera.toml
pyCRT/cameraConfigs/logitechC525.toml
pyCRT/cameraConfigs/x230Integrated.toml
pycrt_dev-2.1.1.dist-info/METADATA
pycrt_dev-2.1.1.dist-info/WHEEL
pycrt_dev-2.1.1.dist-info/licenses/LICENSE
pycrt_dev-2.1.1.dist-info/RECORD
